upsetjs_jupyter_widget/__init__.py
upsetjs_jupyter_widget/_array.py
upsetjs_jupyter_widget/_frontend.py
upsetjs_jupyter_widget/_generate.py
upsetjs_jupyter_widget/_model.py
upsetjs_jupyter_widget/_version.py
upsetjs_jupyter_widget/widget.py
upsetjs_jupyter_widget/labextension/upsetjs-jupyter_widget-1.9.0.tgz
upsetjs_jupyter_widget/nbextension/__init__.py
upsetjs_jupyter_widget/nbextension/static/extension.js
upsetjs_jupyter_widget/nbextension/static/index.js
upsetjs_jupyter_widget/nbextension/static/index.js.LICENSE.txt
upsetjs_jupyter_widget/nbextension/static/index.js.map
upsetjs_jupyter_widget/tests/__init__.py
upsetjs_jupyter_widget/tests/conftest.py
upsetjs_jupyter_widget/tests/test_nbextension_path.py
upsetjs_jupyter_widget/tests/test_widget.py
upsetjs_jupyter_widget-1.9.0.data/data/etc/jupyter/nbconfig/notebook.d/upsetjs_jupyter_widget.json
upsetjs_jupyter_widget-1.9.0.data/data/share/jupyter/lab/extensions/upsetjs-jupyter_widget-1.9.0.tgz
upsetjs_jupyter_widget-1.9.0.data/data/share/jupyter/nbextensions/@upsetjs/jupyter_widget/extension.js
upsetjs_jupyter_widget-1.9.0.data/data/share/jupyter/nbextensions/@upsetjs/jupyter_widget/index.js
upsetjs_jupyter_widget-1.9.0.data/data/share/jupyter/nbextensions/@upsetjs/jupyter_widget/index.js.LICENSE.txt
upsetjs_jupyter_widget-1.9.0.data/data/share/jupyter/nbextensions/@upsetjs/jupyter_widget/index.js.map
upsetjs_jupyter_widget-1.9.0.data/scripts/bump.js
upsetjs_jupyter_widget-1.9.0.dist-info/LICENSE.txt
upsetjs_jupyter_widget-1.9.0.dist-info/METADATA
upsetjs_jupyter_widget-1.9.0.dist-info/WHEEL
upsetjs_jupyter_widget-1.9.0.dist-info/top_level.txt
upsetjs_jupyter_widget-1.9.0.dist-info/RECORD
