Metadata-Version: 2.1
Name: upsetjs-jupyter-widget
Version: 1.9.0
Summary: UpSet.js is a re-implementation of UpSetR to create interactive set visualizations for more than three sets
Home-page: https://github.com/upsetjs/upsetjs_jupyter_widget
Author: Samuel Gratzl
Author-email: sam@sgratzl.com
License: UNKNOWN
Keywords: Jupyter,Widgets,IPython
Platform: Linux
Platform: Mac OS X
Platform: Windows
Classifier: Development Status :: 4 - Beta
Classifier: Intended Audience :: Developers
Classifier: Intended Audience :: Science/Research
Classifier: Intended Audience :: System Administrators
Classifier: License :: Free For Home Use
Classifier: License :: Free for non-commercial use
Classifier: License :: Free For Educational Use
Classifier: Programming Language :: Python
Classifier: Programming Language :: Python :: 3
Classifier: Programming Language :: Python :: 3.6
Classifier: Programming Language :: Python :: 3.7
Classifier: Programming Language :: Python :: 3.8
Classifier: Framework :: IPython
Classifier: Framework :: Jupyter
Classifier: Topic :: Scientific/Engineering :: Information Analysis
Classifier: Topic :: Scientific/Engineering :: Visualization
Classifier: Typing :: Typed
Requires-Dist: ipywidgets (>=7.5.0)
Provides-Extra: docs
Requires-Dist: sphinx (>=1.5) ; extra == 'docs'
Requires-Dist: recommonmark ; extra == 'docs'
Requires-Dist: sphinx-rtd-theme ; extra == 'docs'
Requires-Dist: nbsphinx (<0.4.0,>=0.2.13) ; extra == 'docs'
Requires-Dist: jupyter-sphinx ; extra == 'docs'
Requires-Dist: nbsphinx-link ; extra == 'docs'
Requires-Dist: pytest-check-links ; extra == 'docs'
Requires-Dist: pypandoc ; extra == 'docs'
Provides-Extra: examples
Provides-Extra: test
Requires-Dist: pytest (>=3.6) ; extra == 'test'
Requires-Dist: pytest-cov ; extra == 'test'
Requires-Dist: nbval ; extra == 'test'
